BELM/__init__.py
BELM/belm.py
BELM/belm_copy.py
BELM/net/__init__.py
BELM/net/bslfn.py
BELM/net/bslfn_skcuda.py
PLM/__init__.py
PLM/pelm.py
PLM/pelm_copy1.py
PLM-0.0.0.dist-info/LICENSE.txt
PLM-0.0.0.dist-info/METADATA
PLM-0.0.0.dist-info/WHEEL
PLM-0.0.0.dist-info/top_level.txt
PLM-0.0.0.dist-info/RECORD
