Metadata-Version: 2.1
Name: PLM
Version: 0.0.0
Summary: Bidirectional ELM neural network implementation for regression problem
Home-page: UNKNOWN
Author: Charlie Dondapati
Author-email: cdondapa@lakeheadu.ca
License: BSD (3-clause)
Keywords: BELM PLM  regression
Platform: UNKNOWN
Requires-Dist: hpelm (==1.0.10)
Requires-Dist: numpy (==1.20.1)
Requires-Dist: pandas (==1.2.2)
Requires-Dist: scikit-cuda (==0.5.3)
Requires-Dist: scikit-learn (==0.24.1)
Requires-Dist: scipy (==1.6.1)
Requires-Dist: six (==1.15.0)
Requires-Dist: sklearn (==0.0)
Requires-Dist: tables (==3.6.1)
